{
	"credit": "Made with Blockbench",
	"texture_size": [32, 32],
	"textures": {
		"0": "./hook_dota",
		"particle": "./hook_dota"
	},
	"elements": [
		{
			"from": [7, 16, 8],
			"to": [9, 17, 10],
			"rotation": {"angle": 0, "axis": "y", "origin": [7, 7, 10]},
			"faces": {
				"north": {"uv": [2, 8, 3, 8.5], "texture": "#0"},
				"east": {"uv": [11.5, 8, 12.5, 8.5], "texture": "#0"},
				"south": {"uv": [10, 11.5, 11, 12], "texture": "#0"},
				"west": {"uv": [11, 11.5, 12, 12], "texture": "#0"},
				"up": {"uv": [11.5, 1, 10.5, 0], "texture": "#0"},
				"down": {"uv": [11.5, 1, 10.5, 2], "texture": "#0"}
			}
		},
		{
			"from": [7, 7, 8],
			"to": [9, 8, 10],
			"rotation": {"angle": 0, "axis": "y", "origin": [7, 7, 10]},
			"faces": {
				"north": {"uv": [10, 12, 11, 12.5], "texture": "#0"},
				"east": {"uv": [12, 10, 13, 10.5], "texture": "#0"},
				"south": {"uv": [12, 10.5, 13, 11], "texture": "#0"},
				"west": {"uv": [11, 12, 12, 12.5], "texture": "#0"},
				"up": {"uv": [6.5, 12.5, 5.5, 11.5], "texture": "#0"},
				"down": {"uv": [12.5, 6, 11.5, 7], "texture": "#0"}
			}
		},
		{
			"from": [7.2, 7.2, 8.2],
			"to": [8.8, 16.8, 9.8],
			"rotation": {"angle": 0, "axis": "y", "origin": [7, 7, 10]},
			"faces": {
				"north": {"uv": [0, 0, 1, 5], "texture": "#0"},
				"east": {"uv": [1, 0, 2, 5], "texture": "#0"},
				"south": {"uv": [2, 0, 3, 5], "texture": "#0"},
				"west": {"uv": [3, 0, 4, 5], "texture": "#0"},
				"up": {"uv": [7.5, 12.5, 6.5, 11.5], "texture": "#0"},
				"down": {"uv": [12.5, 7, 11.5, 8], "texture": "#0"}
			}
		},
		{
			"from": [5.35183, 20.93773, 8.09],
			"to": [6.17183, 22.75773, 9.91],
			"rotation": {"angle": -22.5, "axis": "z", "origin": [7, 7, 10]},
			"faces": {
				"north": {"uv": [8, 10, 8.5, 11], "texture": "#0"},
				"east": {"uv": [3.5, 10.5, 4.5, 11.5], "texture": "#0"},
				"south": {"uv": [4.5, 10.5, 5, 11.5], "texture": "#0"},
				"west": {"uv": [10.5, 5.5, 11.5, 6.5], "texture": "#0"},
				"up": {"uv": [2.5, 13, 2, 12], "texture": "#0"},
				"down": {"uv": [9, 12, 8.5, 13], "texture": "#0"}
			}
		},
		{
			"from": [-1.53817, 21.04773, 8.2],
			"to": [6.06183, 22.64773, 9.8],
			"rotation": {"angle": -22.5, "axis": "z", "origin": [7, 7, 10]},
			"faces": {
				"north": {"uv": [4, 0, 8, 1], "texture": "#0"},
				"east": {"uv": [11.5, 2, 12.5, 3], "texture": "#0"},
				"south": {"uv": [4, 1, 8, 2], "texture": "#0"},
				"west": {"uv": [2.5, 11.5, 3.5, 12.5], "texture": "#0"},
				"up": {"uv": [8, 3, 4, 2], "texture": "#0"},
				"down": {"uv": [8, 3, 4, 4], "texture": "#0"}
			}
		},
		{
			"from": [-2.78817, 20.79773, 7.95],
			"to": [-0.68817, 22.89773, 10.05],
			"rotation": {"angle": -22.5, "axis": "z", "origin": [7, 7, 10]},
			"faces": {
				"north": {"uv": [10.5, 6.5, 11.5, 7.5], "texture": "#0"},
				"east": {"uv": [10.5, 7.5, 11.5, 8.5], "texture": "#0"},
				"south": {"uv": [10, 10.5, 11, 11.5], "texture": "#0"},
				"west": {"uv": [11, 4, 12, 5], "texture": "#0"},
				"up": {"uv": [9, 12, 8, 11], "texture": "#0"},
				"down": {"uv": [12, 8.5, 11, 9.5], "texture": "#0"}
			}
		},
		{
			"from": [-0.38949, 18.82371, 8.01],
			"to": [1.59051, 19.80371, 9.99],
			"rotation": {"angle": -45, "axis": "z", "origin": [7, 7, 10]},
			"faces": {
				"north": {"uv": [1, 12, 2, 12.5], "texture": "#0"},
				"east": {"uv": [12, 4, 13, 4.5], "texture": "#0"},
				"south": {"uv": [12, 4.5, 13, 5], "texture": "#0"},
				"west": {"uv": [7.5, 12, 8.5, 12.5], "texture": "#0"},
				"up": {"uv": [11.5, 3, 10.5, 2], "texture": "#0"},
				"down": {"uv": [11.5, 3, 10.5, 4], "texture": "#0"}
			}
		},
		{
			"from": [-0.38949, 13.82371, 8.01],
			"to": [1.59051, 14.80371, 9.99],
			"rotation": {"angle": -45, "axis": "z", "origin": [7, 7, 10]},
			"faces": {
				"north": {"uv": [12, 8.5, 13, 9], "texture": "#0"},
				"east": {"uv": [9, 12, 10, 12.5], "texture": "#0"},
				"south": {"uv": [12, 9, 13, 9.5], "texture": "#0"},
				"west": {"uv": [12, 9.5, 13, 10], "texture": "#0"},
				"up": {"uv": [12.5, 4, 11.5, 3], "texture": "#0"},
				"down": {"uv": [4.5, 11.5, 3.5, 12.5], "texture": "#0"}
			}
		},
		{
			"from": [-0.19949, 14.01371, 8.2],
			"to": [1.40051, 19.61371, 9.8],
			"rotation": {"angle": -45, "axis": "z", "origin": [7, 7, 10]},
			"faces": {
				"north": {"uv": [4, 4, 5, 7], "texture": "#0"},
				"east": {"uv": [0, 5, 1, 8], "texture": "#0"},
				"south": {"uv": [1, 5, 2, 8], "texture": "#0"},
				"west": {"uv": [2, 5, 3, 8], "texture": "#0"},
				"up": {"uv": [5.5, 12.5, 4.5, 11.5], "texture": "#0"},
				"down": {"uv": [12.5, 5, 11.5, 6], "texture": "#0"}
			}
		},
		{
			"from": [-2.49457, 17.23402, 8.2],
			"to": [-0.89457, 20.83402, 9.8],
			"rotation": {"angle": -22.5, "axis": "z", "origin": [7, 7, 10]},
			"faces": {
				"north": {"uv": [3, 5, 4, 7], "texture": "#0"},
				"east": {"uv": [4, 8.5, 5, 10.5], "texture": "#0"},
				"south": {"uv": [9.5, 0, 10.5, 2], "texture": "#0"},
				"west": {"uv": [9.5, 2, 10.5, 4], "texture": "#0"},
				"up": {"uv": [10, 12, 9, 11], "texture": "#0"},
				"down": {"uv": [12, 9.5, 11, 10.5], "texture": "#0"}
			}
		},
		{
			"from": [2.41046, 18.05432, 8.3],
			"to": [3.81046, 20.45432, 9.7],
			"rotation": {"angle": 0, "axis": "y", "origin": [7, 7, 10]},
			"faces": {
				"north": {"uv": [2.5, 10, 3.5, 11.5], "texture": "#0"},
				"east": {"uv": [10, 4, 11, 5.5], "texture": "#0"},
				"south": {"uv": [7, 10, 8, 11.5], "texture": "#0"},
				"west": {"uv": [10, 9, 11, 10.5], "texture": "#0"},
				"up": {"uv": [12, 11.5, 11, 10.5], "texture": "#0"},
				"down": {"uv": [1, 11.5, 0, 12.5], "texture": "#0"}
			}
		},
		{
			"from": [7.12446, 15.94773, 8.5],
			"to": [8.12446, 18.94773, 9.5],
			"rotation": {"angle": 22.5, "axis": "z", "origin": [7, 7, 10]},
			"faces": {
				"north": {"uv": [5, 9.5, 6, 11.5], "texture": "#0"},
				"east": {"uv": [9.5, 5.5, 10.5, 7.5], "texture": "#0"},
				"south": {"uv": [6, 9.5, 7, 11.5], "texture": "#0"},
				"west": {"uv": [1.5, 10, 2.5, 12], "texture": "#0"},
				"up": {"uv": [12.5, 1, 11.5, 0], "texture": "#0"},
				"down": {"uv": [12.5, 1, 11.5, 2], "texture": "#0"}
			}
		},
		{
			"from": [6.5, 3.1, 9],
			"to": [9.5, 7.1, 9],
			"faces": {
				"north": {"uv": [6.5, 4, 8, 6], "texture": "#0"},
				"east": {"uv": [0, 0, 0, 2], "texture": "#0"},
				"south": {"uv": [6.5, 6, 8, 8], "texture": "#0"},
				"west": {"uv": [0, 0, 0, 2], "texture": "#0"},
				"up": {"uv": [1.5, 0, 0, 0], "texture": "#0"},
				"down": {"uv": [1.5, 0, 0, 0], "texture": "#0"}
			}
		},
		{
			"from": [10, 0, 9],
			"to": [14, 3, 9],
			"rotation": {"angle": 45, "axis": "z", "origin": [10, 2, 9]},
			"faces": {
				"north": {"uv": [3, 7, 5, 8.5], "texture": "#0"},
				"east": {"uv": [0, 0, 0, 1.5], "texture": "#0"},
				"south": {"uv": [0, 8, 2, 9.5], "texture": "#0"},
				"west": {"uv": [0, 0, 0, 1.5], "texture": "#0"},
				"up": {"uv": [2, 0, 0, 0], "texture": "#0"},
				"down": {"uv": [2, 0, 0, 0], "texture": "#0"}
			}
		},
		{
			"from": [12.37868, 4.35025, 9],
			"to": [15.37868, 8.35025, 9],
			"rotation": {"angle": -22.5, "axis": "z", "origin": [15, 4, 9]},
			"faces": {
				"north": {"uv": [0, 8, 2, 9.5], "rotation": 90, "texture": "#0"},
				"east": {"uv": [2, 0, 0, 0], "rotation": 270, "texture": "#0"},
				"south": {"uv": [3, 7, 5, 8.5], "rotation": 270, "texture": "#0"},
				"west": {"uv": [2, 0, 0, 0], "rotation": 270, "texture": "#0"},
				"up": {"uv": [0, 0, 0, 1.5], "rotation": 270, "texture": "#0"},
				"down": {"uv": [0, 0, 0, 1.5], "rotation": 270, "texture": "#0"}
			}
		},
		{
			"from": [6.8, -0.7, 9],
			"to": [10.8, 2.3, 9],
			"rotation": {"angle": -22.5, "axis": "z", "origin": [8, 2, 9]},
			"faces": {
				"north": {"uv": [3, 7, 5, 8.5], "texture": "#0"},
				"east": {"uv": [0, 0, 0, 1.5], "texture": "#0"},
				"south": {"uv": [0, 8, 2, 9.5], "texture": "#0"},
				"west": {"uv": [0, 0, 0, 1.5], "texture": "#0"},
				"up": {"uv": [2, 0, 0, 0], "texture": "#0"},
				"down": {"uv": [2, 0, 0, 0], "texture": "#0"}
			}
		},
		{
			"from": [8, 1, 7.5],
			"to": [8, 5, 10.5],
			"faces": {
				"north": {"uv": [0, 0, 0, 2], "texture": "#0"},
				"east": {"uv": [6.5, 4, 8, 6], "texture": "#0"},
				"south": {"uv": [0, 0, 0, 2], "texture": "#0"},
				"west": {"uv": [6.5, 6, 8, 8], "texture": "#0"},
				"up": {"uv": [0, 1.5, 0, 0], "texture": "#0"},
				"down": {"uv": [0, 0, 0, 1.5], "texture": "#0"}
			}
		},
		{
			"from": [9.3, -1.4, 7.5],
			"to": [9.3, 2.6, 10.5],
			"rotation": {"angle": -45, "axis": "z", "origin": [11, 0, 8]},
			"faces": {
				"north": {"uv": [0, 0, 0, 2], "texture": "#0"},
				"east": {"uv": [6.5, 4, 8, 6], "texture": "#0"},
				"south": {"uv": [0, 0, 0, 2], "texture": "#0"},
				"west": {"uv": [6.5, 6, 8, 8], "texture": "#0"},
				"up": {"uv": [0, 1.5, 0, 0], "texture": "#0"},
				"down": {"uv": [0, 0, 0, 1.5], "texture": "#0"}
			}
		},
		{
			"from": [9.1, 2.9, 7.5],
			"to": [9.1, 6.9, 10.5],
			"rotation": {"angle": -45, "axis": "z", "origin": [11, 0, 8]},
			"faces": {
				"north": {"uv": [0, 0, 0, 2], "texture": "#0"},
				"east": {"uv": [6.5, 6, 8, 8], "texture": "#0"},
				"south": {"uv": [0, 0, 0, 2], "texture": "#0"},
				"west": {"uv": [6.5, 4, 8, 6], "texture": "#0"},
				"up": {"uv": [0, 1.5, 0, 0], "texture": "#0"},
				"down": {"uv": [0, 0, 0, 1.5], "texture": "#0"}
			}
		},
		{
			"from": [15.42132, 6.30761, 7.5],
			"to": [15.42132, 10.30761, 10.5],
			"rotation": {"angle": 0, "axis": "y", "origin": [16, 8, 8]},
			"faces": {
				"north": {"uv": [0, 0, 0, 2], "texture": "#0"},
				"east": {"uv": [6.5, 6, 8, 8], "texture": "#0"},
				"south": {"uv": [0, 0, 0, 2], "texture": "#0"},
				"west": {"uv": [6.5, 4, 8, 6], "texture": "#0"},
				"up": {"uv": [0, 1.5, 0, 0], "texture": "#0"},
				"down": {"uv": [0, 0, 0, 1.5], "texture": "#0"}
			}
		}
	],
	"display": {
		"thirdperson_righthand": {
			"rotation": [0, -90, 0],
			"translation": [1, -5.25, 0.75]
		},
		"thirdperson_lefthand": {
			"rotation": [0, 90, 0],
			"translation": [-1, -5.25, 0.75]
		},
		"firstperson_righthand": {
			"rotation": [0, -82, 0],
			"translation": [1, -3.25, 0]
		},
		"firstperson_lefthand": {
			"rotation": [0, 92, 0],
			"translation": [0, -3.25, 0]
		},
		"ground": {
			"rotation": [90, 0, 0],
			"translation": [0, -1.25, 0],
			"scale": [0.9, 0.9, 0.9]
		},
		"gui": {
			"rotation": [-180, 28, -154.75],
			"translation": [-3, -7, 0]
		},
		"head": {
			"rotation": [-39.5, -90, 0],
			"translation": [1, -0.75, 15],
			"scale": [1.2, 1.2, 1.2]
		},
		"fixed": {
			"translation": [0, -7.25, -3.5],
			"scale": [1.7, 1.7, 1.7]
		}
	},
	"groups": [
		{
			"name": "group",
			"origin": [7, -4, 8],
			"color": 0,
			"children": [0, 1, 2, 3, 4, 5, 6, 7, 8, 9, 10, 11]
		},
		{
			"name": "group2",
			"origin": [8, 8, 8],
			"color": 0,
			"children": [12, 13, 14, 15, 16, 17, 18, 19]
		}
	]
}